{
  "total_nodes": 390,
  "total_edges": 9495,
  "node_types": {
    "document": 369,
    "heritage_type": 6,
    "domain": 6,
    "time_period": 3,
    "region": 6
  },
  "edge_types": {
    "has_type": 727,
    "belongs_to_domain": 1066,
    "from_period": 321,
    "located_in_region": 247,
    "similar_to": 606,
    "same_cluster": 6528
  },
  "density": 0.12517302748665216,
  "average_degree": 48.69230769230769,
  "is_connected": true,
  "number_of_components": 1,
  "creation_date": "2025-10-30T22:55:16.907228",
  "top_central_documents": [
    {
      "title": "List of heritage registers",
      "centrality": 0.2185089974293059
    },
    {
      "title": "Intangible cultural heritage",
      "centrality": 0.19023136246786632
    },
    {
      "title": "Heritage conservation in Canada",
      "centrality": 0.18251928020565553
    },
    {
      "title": "Conservation and restoration of cultural property",
      "centrality": 0.1773778920308483
    },
    {
      "title": "Conservation and restoration of cultural property",
      "centrality": 0.1773778920308483
    },
    {
      "title": "World Heritage Sites by country",
      "centrality": 0.1748071979434447
    },
    {
      "title": "World Heritage Site",
      "centrality": 0.16709511568123392
    },
    {
      "title": "History of India",
      "centrality": 0.16709511568123392
    },
    {
      "title": "Historic preservation",
      "centrality": 0.16709511568123392
    },
    {
      "title": "Sculpture",
      "centrality": 0.16709511568123392
    }
  ]
}